pyinpaint/__init__.py
pyinpaint/__main__.py
pyinpaint/inpaint.py
pyinpaint/utils.py
pyinpaint-1.0.0.dist-info/LICENSE
pyinpaint-1.0.0.dist-info/METADATA
pyinpaint-1.0.0.dist-info/WHEEL
pyinpaint-1.0.0.dist-info/entry_points.txt
pyinpaint-1.0.0.dist-info/top_level.txt
pyinpaint-1.0.0.dist-info/RECORD
